pybioprox_gui.py
pybioprox/__init__.py
pybioprox/__main__.py
pybioprox/cli.py
pybioprox/distance_analysis.py
pybioprox/main.py
pybioprox/utility.py
pybioprox-1.0.3.dist-info/LICENSE.txt
pybioprox-1.0.3.dist-info/METADATA
pybioprox-1.0.3.dist-info/WHEEL
pybioprox-1.0.3.dist-info/entry_points.txt
pybioprox-1.0.3.dist-info/top_level.txt
pybioprox-1.0.3.dist-info/RECORD
