Metadata-Version: 2.1
Name: pybioprox
Version: 1.0.3
Summary: Distance-based colocalisation analysis module
Home-page: https://github.com/PyBioProx/pybioprox
Author: Jeremy Metz
Author-email: j.metz@exeter.ac.uk
License: AGPLv3
Project-URL: Bug Tracker, https://github.com/pybioprox/pybioprox/issues
Platform: any
Classifier: Development Status :: 3 - Alpha
Classifier: Intended Audience :: Developers
Classifier: License :: OSI Approved :: MIT License
Classifier: Operating System :: OS Independent
Classifier: Programming Language :: Python
Classifier: Programming Language :: Python :: 3.4
Classifier: Programming Language :: Python :: 3.5
Classifier: Programming Language :: Python :: 3.6
Classifier: Programming Language :: Python :: 3.7
Classifier: Programming Language :: Python :: 3.8
Classifier: Topic :: Software Development :: Libraries :: Python Modules
Requires-Python: >=3.4
Requires-Dist: imageio (>=2.6.1)
Requires-Dist: scipy (>=1.4.1)
Requires-Dist: scikit-image (>=0.16.2)
Requires-Dist: colorama (>=0.4.3)
Requires-Dist: coloredlogs (>=14.0)
Requires-Dist: pandas (>=1.0.3)
Requires-Dist: numpy (>=1.18)
Requires-Dist: tifffile (>=2020.2.16)
Requires-Dist: matplotlib (>=3.2.1)
Provides-Extra: dev
Requires-Dist: coverage (>=5.2) ; extra == 'dev'
Requires-Dist: PyQt5 ; extra == 'dev'
Requires-Dist: pytest-qt ; extra == 'dev'
Provides-Extra: gui
Requires-Dist: PyQt5 ; extra == 'gui'
